mypy_clean_slate/__init__.py
mypy_clean_slate/main.py
mypy_clean_slate-0.4.0.dist-info/METADATA
mypy_clean_slate-0.4.0.dist-info/WHEEL
mypy_clean_slate-0.4.0.dist-info/entry_points.txt
mypy_clean_slate-0.4.0.dist-info/licenses/LICENSE
mypy_clean_slate-0.4.0.dist-info/RECORD
