Metadata-Version: 2.4
Name: mypy_clean_slate
Version: 0.4.0
Summary: CLI tool for providing a clean slate for mypy usage within a project.
Project-URL: Homepage, https://github.com/geo7/mypy_clean_slate
Author-email: George Lenton <georgelenton@gmail.com>
License: MIT
License-File: LICENSE
Keywords: mypy,type-hint,typehint,typing
Requires-Python: >=3.9
Requires-Dist: mypy<2.0,>=0.910
Provides-Extra: dev
Requires-Dist: ipdb<0.14.0,>=0.13.9; extra == 'dev'
Requires-Dist: ipython>=8.18.1; extra == 'dev'
Requires-Dist: pdbpp<0.12.0,>=0.10.3; extra == 'dev'
Requires-Dist: pre-commit>=4.0.0; extra == 'dev'
Requires-Dist: pytest-cov>=5.0.0; extra == 'dev'
Requires-Dist: pytest<9.0.0,>=8.0.0; extra == 'dev'
Requires-Dist: ruff>=0.0.265; extra == 'dev'
